randovania/__init__.py
randovania/__main__.py
randovania/version.py
randovania/version_hash.py
randovania/bitpacking/__init__.py
randovania/bitpacking/bitpacking.py
randovania/bitpacking/json_dataclass.py
randovania/bitpacking/type_enforcement.py
randovania/cli/__init__.py
randovania/cli/cli_lib.py
randovania/cli/database.py
randovania/cli/development.py
randovania/cli/gui.py
randovania/cli/layout.py
randovania/cli/server.py
randovania/cli/commands/__init__.py
randovania/cli/commands/batch_distribute.py
randovania/cli/commands/export_db_videos.py
randovania/cli/commands/generate.py
randovania/cli/commands/patcher_data.py
randovania/cli/commands/permalink.py
randovania/cli/commands/refresh_presets.py
randovania/cli/commands/validate.py
randovania/data/.gitignore
randovania/data/migration_data.json
randovania/data/ClarisEchoesMenu/EchoesMenu.exe
randovania/data/ClarisEchoesMenu/liblzo2.dylib
randovania/data/ClarisEchoesMenu/liblzo2.so
randovania/data/ClarisEchoesMenu/lzo2.dll
randovania/data/ClarisEchoesMenu/readme.txt
randovania/data/ClarisPrimeRandomizer/.gitignore
randovania/data/ClarisPrimeRandomizer/Randomizer.exe
randovania/data/ClarisPrimeRandomizer/RandomizerData.json
randovania/data/ClarisPrimeRandomizer/liblzo2.dylib
randovania/data/ClarisPrimeRandomizer/liblzo2.so
randovania/data/ClarisPrimeRandomizer/lzo2.dll
randovania/data/ClarisPrimeRandomizer/readme.txt
randovania/data/ClarisPrimeRandomizer/zlib1.dll
randovania/data/binary_data/.gitignore
randovania/data/binary_data/CREDITS.txt
randovania/data/gui_assets/database-example.png
randovania/data/gui_assets/database-open.png
randovania/data/gui_assets/tracker-open.png
randovania/data/gui_assets/tracker/dread-game.json
randovania/data/gui_assets/tracker/prime1-game-eight-lines.json
randovania/data/gui_assets/tracker/prime1-game-three-lines.json
randovania/data/gui_assets/tracker/prime1-game-two-lines.json
randovania/data/gui_assets/tracker/prime1-game.json
randovania-5.8.0.dist-info/LICENSE
randovania-5.8.0.dist-info/METADATA
randovania-5.8.0.dist-info/WHEEL
randovania-5.8.0.dist-info/entry_points.txt
randovania-5.8.0.dist-info/top_level.txt
randovania-5.8.0.dist-info/RECORD
