Metadata-Version: 2.1
Name: randovania
Version: 5.8.0
Summary: A randomizer platform for a multitude of games.
Home-page: https://github.com/randovania/randovania
Author: Henrique Gemignani Passos Lima
Classifier: Development Status :: 5 - Production/Stable
Classifier: Environment :: Console
Classifier: Environment :: Win32 (MS Windows)
Classifier: Environment :: X11 Applications :: Qt
Classifier: Intended Audience :: End Users/Desktop
Classifier: License :: OSI Approved :: GNU General Public License v3 or later (GPLv3+)
Classifier: Programming Language :: Python :: 3 :: Only
Classifier: Programming Language :: Python :: 3.11
Classifier: Topic :: Games/Entertainment
Requires-Python: >=3.11
License-File: LICENSE
Requires-Dist: networkx
Requires-Dist: bitstruct
Requires-Dist: construct
Requires-Dist: tenacity (>=7.0.0)
Requires-Dist: python-slugify
Requires-Dist: python-socketio[asyncio_client]
Requires-Dist: aiohttp
Requires-Dist: aiofiles
Requires-Dist: attrs (>=21.4.0)
Requires-Dist: frozendict
Requires-Dist: dulwich (>=0.20)
Requires-Dist: py-randomprime (>=1.13.0)
Requires-Dist: mp2hudcolor (>=1.0.10)
Requires-Dist: retro-data-structures (>=0.15.2)
Requires-Dist: SuperDuperMetroid (>=1.2.0)
Requires-Dist: open-dread-rando (>=1.6.0)
Requires-Dist: open-prime-rando (>=0.4.2)
Requires-Dist: cave-story-randomizer (>=1.0.0)
Requires-Dist: tsc-utils (>=0.2.0)
Requires-Dist: random-enemy-attributes (>=1.0.3)
Requires-Dist: sentry-sdk
Provides-Extra: gui
Requires-Dist: PySide6-Essentials (>=6.4.0.1) ; extra == 'gui'
Requires-Dist: appdirs ; extra == 'gui'
Requires-Dist: qasync ; extra == 'gui'
Requires-Dist: async-wiiload ; extra == 'gui'
Requires-Dist: dolphin-memory-engine (>=1.0.2) ; extra == 'gui'
Requires-Dist: markdown ; extra == 'gui'
Requires-Dist: matplotlib (>=3.6.2) ; extra == 'gui'
Requires-Dist: nod (>=1.9) ; extra == 'gui'
Requires-Dist: pid (>=3.0.0) ; extra == 'gui'
Requires-Dist: pypresence ; extra == 'gui'
Requires-Dist: pyqtdarktheme ; extra == 'gui'
Provides-Extra: server
Requires-Dist: cryptography ; extra == 'server'
Requires-Dist: py-cord (>=2.3.1) ; extra == 'server'
Requires-Dist: eventlet ; extra == 'server'
Requires-Dist: flask-discord ; extra == 'server'
Requires-Dist: flask-socketio ; extra == 'server'
Requires-Dist: prometheus-flask-exporter ; extra == 'server'
Requires-Dist: peewee ; extra == 'server'
Requires-Dist: requests-oauthlib ; extra == 'server'
Requires-Dist: Pillow (>=9.0.0) ; extra == 'server'
Requires-Dist: graphviz ; extra == 'server'
Requires-Dist: sentry-sdk[flask] ; extra == 'server'
Requires-Dist: cachetools ; extra == 'server'
Provides-Extra: test
Requires-Dist: pytest ; extra == 'test'
Requires-Dist: pytest-cov ; extra == 'test'
Requires-Dist: pytest-qt ; extra == 'test'
Requires-Dist: pytest-asyncio ; extra == 'test'
Requires-Dist: pytest-mock ; extra == 'test'
Requires-Dist: pytest-localftpserver ; extra == 'test'
Requires-Dist: pytest-xdist[psutil] ; extra == 'test'
Requires-Dist: mock (>=4.0) ; extra == 'test'
